hikugen/__init__.py
hikugen/code_generator.py
hikugen/code_validation.py
hikugen/database.py
hikugen/extractor.py
hikugen/http_client.py
hikugen/prompts.py
hikugen-0.2.1.dist-info/licenses/LICENSE
hikugen-0.2.1.dist-info/METADATA
hikugen-0.2.1.dist-info/WHEEL
hikugen-0.2.1.dist-info/top_level.txt
hikugen-0.2.1.dist-info/RECORD
