Metadata-Version: 2.4
Name: hikugen
Version: 0.2.1
Summary: AI-powered web scraping library that generates Python code to extract structured data into Pydantic schemas
Requires-Python: >=3.11
License-File: LICENSE
Requires-Dist: beautifulsoup4>=4.13.5
Requires-Dist: pydantic>=2.11.9
Requires-Dist: pytest>=8.4.2
Requires-Dist: requests>=2.32.5
Requires-Dist: ruff>=0.13.2
Dynamic: license-file
